sadrive/__init__.py
sadrive/cli.py
sadrive/commands/__init__.py
sadrive/commands/config.py
sadrive/commands/db.py
sadrive/commands/delete.py
sadrive/commands/downlaod.py
sadrive/commands/manipulation.py
sadrive/commands/navigate.py
sadrive/commands/upload.py
sadrive/helpers/__init__.py
sadrive/helpers/dbf.py
sadrive/helpers/drive.py
sadrive/helpers/utils.py
sadrive-2.0.2.dist-info/licenses/LICENSE
sadrive-2.0.2.dist-info/METADATA
sadrive-2.0.2.dist-info/WHEEL
sadrive-2.0.2.dist-info/entry_points.txt
sadrive-2.0.2.dist-info/top_level.txt
sadrive-2.0.2.dist-info/RECORD
