Metadata-Version: 2.4
Name: sadrive
Version: 2.0.2
Summary: Use many service accounts as a unified google storage, with mounting to filesystem, and parallel uploads/downloads.
Home-page: https://github.com/jsmaskeen/sa-drive
Author: jsmaskeen
Author-email: jsmaskeen@gmail.com
License: GPL-3.0-or-later
Keywords: python,service accounts,unlimited storage,file system,google drive,shared drive,teamdrive,sadrive
Classifier: Development Status :: 5 - Production/Stable
Classifier: Intended Audience :: Developers
Classifier: Programming Language :: Python :: 3.10
Classifier: Operating System :: OS Independent
Classifier: Topic :: Software Development :: Libraries :: Python Modules
Classifier: Typing :: Typed
Requires-Python: >=3.11
License-File: LICENSE
Requires-Dist: ansicon==1.89.0
Requires-Dist: blessed==1.21.0
Requires-Dist: cachetools==5.5.2
Requires-Dist: certifi==2025.6.15
Requires-Dist: cffi==1.17.1
Requires-Dist: charset-normalizer==3.4.2
Requires-Dist: click==8.2.1
Requires-Dist: colorama==0.4.6
Requires-Dist: cryptography==43.0.3
Requires-Dist: editor==1.6.6
Requires-Dist: google-api-core==2.25.1
Requires-Dist: google-api-python-client==2.172.0
Requires-Dist: google-api-python-client-stubs==1.29.0
Requires-Dist: google-auth==2.40.3
Requires-Dist: google-auth-httplib2==0.2.0
Requires-Dist: googleapis-common-protos==1.70.0
Requires-Dist: httplib2==0.22.0
Requires-Dist: idna==3.10
Requires-Dist: inquirer==3.4.0
Requires-Dist: jinxed==1.3.0
Requires-Dist: markdown-it-py==3.0.0
Requires-Dist: mdurl==0.1.2
Requires-Dist: oauth2client==4.1.3
Requires-Dist: prettytable==3.16.0
Requires-Dist: proto-plus==1.26.1
Requires-Dist: protobuf==6.31.1
Requires-Dist: pyasn1==0.6.1
Requires-Dist: pyasn1_modules==0.4.2
Requires-Dist: pycparser==2.22
Requires-Dist: PyDrive2==1.21.3
Requires-Dist: Pygments==2.19.1
Requires-Dist: pyOpenSSL==24.2.1
Requires-Dist: pyparsing==3.2.3
Requires-Dist: PyYAML==6.0.2
Requires-Dist: readchar==4.2.1
Requires-Dist: requests==2.32.4
Requires-Dist: rich==14.0.0
Requires-Dist: rsa==4.9.1
Requires-Dist: runs==1.2.2
Requires-Dist: six==1.17.0
Requires-Dist: types-httplib2==0.22.0.20250516
Requires-Dist: typing_extensions==4.14.0
Requires-Dist: uritemplate==4.2.0
Requires-Dist: urllib3==2.5.0
Requires-Dist: wcwidth==0.2.13
Requires-Dist: xmod==1.8.1
Dynamic: author
Dynamic: author-email
Dynamic: classifier
Dynamic: description
Dynamic: description-content-type
Dynamic: home-page
Dynamic: keywords
Dynamic: license
Dynamic: license-file
Dynamic: requires-dist
Dynamic: requires-python
Dynamic: summary
